crustypy_instance/__init__.py
crustypy_instance/_crustypy_instance.py
crustypy_instance/py.typed
crustypy_instance-0.1.1.dist-info/LICENSE
crustypy_instance-0.1.1.dist-info/METADATA
crustypy_instance-0.1.1.dist-info/WHEEL
crustypy_instance-0.1.1.dist-info/RECORD
