Metadata-Version: 2.1
Name: crustypy-instance
Version: 0.1.1
Summary: Generated with CrustyPy.
Home-page: https://github.com/MicaelJarniac/crustypy-instance
License: MIT
Author: Micael Jarniac
Author-email: micael@jarniac.dev
Requires-Python: >=3.8,<4.0
Classifier: Development Status :: 1 - Planning
Classifier: License :: OSI Approved :: MIT License
Classifier: Natural Language :: English
Classifier: Operating System :: OS Independent
Classifier: Programming Language :: Python :: 3
Classifier: Programming Language :: Python :: 3.8
Classifier: Programming Language :: Python :: 3.9
Classifier: Programming Language :: Python :: 3.10
Classifier: Programming Language :: Python :: 3.11
Classifier: Typing :: Typed
Requires-Dist: loguru (>=0.7.0,<0.8.0)
Project-URL: Bug Tracker, https://github.com/MicaelJarniac/crustypy-instance/issues
Project-URL: Changelog, https://github.com/MicaelJarniac/crustypy-instance/blob/main/docs/CHANGELOG.md
Project-URL: Documentation, https://crustypy-instance.readthedocs.io
Project-URL: Repository, https://github.com/MicaelJarniac/crustypy-instance
